{
  "sheet": "Metro Persons in Household",
  "data": {
    "Albuquerque": [
      22509,
      11747,
      3908,
      3280,
      null,
      "Source: 2017 American Community Survey, 1-Year Estimates, US Census Bureau "
    ],
    "Atlanta": [
      171947,
      106857,
      49760,
      42832
    ],
    "Austin": [
      92079,
      55429,
      19314,
      17342
    ],
    "Baltimore": [
      96666,
      45793,
      17789,
      17155
    ],
    "Birmingham": [
      32707,
      16017,
      6520,
      3642
    ],
    "Boston": [
      177562,
      101413,
      40854,
      25675
    ],
    "Charleston": [
      21318,
      11245,
      5571,
      4643
    ],
    "Charlotte": [
      67757,
      38254,
      16654,
      16173
    ],
    "Chicago": [
      334095,
      178047,
      63419,
      58820
    ],
    "Cincinnati": [
      72635,
      33812,
      12617,
      10812
    ],
    "Cleveland": [
      89312,
      36442,
      9473,
      7023
    ],
    "Columbus": [
      67151,
      35553,
      12470,
      14395
    ],
    "Dallas Fort Worth": [
      273640,
      162387,
      79106,
      83819
    ],
    "Denver": [
      115463,
      78203,
      24538,
      22983
    ],
    "Detroit": [
      135532,
      60836,
      21616,
      12584
    ],
    "Houston": [
      230095,
      150390,
      66435,
      88228
    ],
    "Indianapolis": [
      67949,
      29875,
      8867,
      9326
    ],
    "Kansas City": [
      70691,
      33471,
      9213,
      8820
    ],
    "Las Vegas": [
      72900,
      45004,
      18657,
      22354
    ],
    "Little Rock": [
      20433,
      10048,
      6433,
      4333
    ],
    "Los Angeles": [
      477506,
      360125,
      181680,
      241296
    ],
    "Louisville": [
      36822,
      15625,
      8057,
      3325
    ],
    "Memphis": [
      37604,
      16755,
      7867,
      8010
    ],
    "Miami": [
      195979,
      146687,
      75800,
      64204
    ],
    "Milwaukee": [
      71793,
      31882,
      8094,
      7117
    ],
    "Minneapolis": [
      146701,
      69188,
      22695,
      21348
    ],
    "Nashville": [
      55636,
      37501,
      14474,
      18060
    ],
    "New Orleans": [
      37182,
      14891,
      5051,
      3978
    ],
    "New York City": [
      908559,
      634413,
      316032,
      354824
    ],
    "Oklahoma City": [
      37718,
      18520,
      6610,
      5394
    ],
    "Orlando": [
      64045,
      52251,
      27504,
      25535
    ],
    "Philadelphia": [
      191148,
      83069,
      30247,
      21751
    ],
    "Phoenix": [
      134653,
      74189,
      28702,
      32776
    ],
    "Pittsburgh": [
      80468,
      26492,
      7273,
      4525
    ],
    "Portland": [
      87580,
      53932,
      19099,
      18021
    ],
    "Raleigh": [
      36669,
      22253,
      8963,
      9540
    ],
    "Richmond": [
      36134,
      17591,
      8213,
      6981
    ],
    "Riverside": [
      57219,
      46224,
      24687,
      36624
    ],
    "Sacramento": [
      59227,
      41598,
      18212,
      20179
    ],
    "St. Louis": [
      76066,
      32273,
      12932,
      5629
    ],
    "Salt Lake City": [
      27833,
      17489,
      9176,
      9073
    ],
    "San Antonio": [
      69569,
      38906,
      17936,
      14932
    ],
    "San Diego": [
      97177,
      91044,
      42062,
      46432
    ],
    "San Francisco": [
      180861,
      128902,
      48940,
      53148
    ],
    "San Jose": [
      49230,
      47833,
      23472,
      25302
    ],
    "Seattle": [
      173025,
      111290,
      34518,
      37208
    ],
    "Sioux Falls": [
      11731,
      5374,
      3051,
      1177
    ],
    "Tampa": [
      89228,
      52804,
      23692,
      17489
    ],
    "Honolulu": [
      30538,
      20721,
      8083,
      9316
    ],
    "Washington D.C.": [
      238357,
      152203,
      64632,
      74250
    ],
    "Ann Arbor": [
      15598,
      11449,
      3344,
      2178
    ]
  },
  "labels": [
    1,
    2,
    3,
    "4+",
    null,
    "Time Period: 2017"
  ]
}